ecashrpc/__init__.py
ecashrpc/__version__.py
ecashrpc/_exceptions.py
ecashrpc/_types.py
ecashrpc/ecash_rpc.py
ecashrpc-0.0.1.dist-info/LICENSE
ecashrpc-0.0.1.dist-info/METADATA
ecashrpc-0.0.1.dist-info/WHEEL
ecashrpc-0.0.1.dist-info/top_level.txt
ecashrpc-0.0.1.dist-info/RECORD
