Metadata-Version: 2.1
Name: ecashrpc
Version: 0.0.1
Summary: eCash JSON-RPC Python module
Home-page: https://github.com/ethanmackie/eCash-Python-RPC
Author: Ethan Quintera
Author-email: ethanmackie1199@gmail.com
License: MIT
Keywords: eCash XEC bitcoin ABC async json-rpc avalanche post-consensus
Classifier: Development Status :: 4 - Beta
Classifier: Intended Audience :: Developers
Classifier: Programming Language :: Python
Classifier: Programming Language :: Python :: 3.7
Classifier: Programming Language :: Python :: 3.8
Classifier: Programming Language :: Python :: 3.9
Classifier: Programming Language :: Python :: 3.10
Classifier: Programming Language :: Python :: 3 :: Only
Classifier: Topic :: Software Development :: Libraries :: Python Modules
Requires-Python: >=3.7
License-File: LICENSE
